ptpdb/toolbars.py
ptpdb/key_bindings.py
ptpdb/completion_hints.py
ptpdb/commands.py
ptpdb/completers.py
ptpdb/style.py
ptpdb/grammar.py
ptpdb/layout.py
ptpdb/__init__.py
ptpdb-0.17.dist-info/DESCRIPTION.rst
ptpdb-0.17.dist-info/METADATA
ptpdb-0.17.dist-info/top_level.txt
ptpdb-0.17.dist-info/RECORD
ptpdb-0.17.dist-info/metadata.json
ptpdb-0.17.dist-info/WHEEL
