Metadata-Version: 2.0
Name: ptpdb
Version: 0.17
Summary: Python debugger (pdb) build on top of prompt_toolkit
Home-page: https://github.com/jonathanslenders/ptpdb
Author: Jonathan Slenders
Author-email: UNKNOWN
License: UNKNOWN
Platform: UNKNOWN
Requires-Dist: ptpython (==0.33)
Requires-Dist: prompt-toolkit (>=1.0.0,<2.0.0)
